stormware/__init__.py
stormware/auth.py
stormware/client_manager.py
stormware/facebook.py
stormware/py.typed
stormware/secrets.py
stormware/amazon/__init__.py
stormware/amazon/auth.py
stormware/amazon/secrets.py
stormware/google/__init__.py
stormware/google/auth.py
stormware/google/bigquery.py
stormware/google/drive.py
stormware/google/gmail.py
stormware/google/secrets.py
stormware/google/sheets.py
stormware-2.2.1.dist-info/licenses/LICENSE.txt
stormware-2.2.1.dist-info/METADATA
stormware-2.2.1.dist-info/WHEEL
stormware-2.2.1.dist-info/top_level.txt
stormware-2.2.1.dist-info/RECORD
