Metadata-Version: 2.4
Name: stormware
Version: 2.2.1
Summary: API connectors for data analysis and task automation
Author-email: Logikal GmbH <contact@logikal.io>
License-Expression: MIT
Project-URL: Documentation, https://docs.logikal.io/stormware/
Project-URL: Release notes, https://github.com/logikal-io/stormware/releases
Project-URL: Issue tracker, https://github.com/logikal-io/stormware/issues
Project-URL: Source code, https://github.com/logikal-io/stormware
Keywords: api,connector
Classifier: Development Status :: 5 - Production/Stable
Classifier: Intended Audience :: Developers
Classifier: Operating System :: POSIX :: Linux
Classifier: Programming Language :: Python :: 3
Classifier: Programming Language :: Python :: 3.12
Classifier: Topic :: Software Development :: Libraries :: Python Modules
Classifier: Typing :: Typed
Requires-Python: ~=3.12
License-File: LICENSE.txt
Requires-Dist: logikal-utils~=1.4
Requires-Dist: pandas~=2.2
Requires-Dist: pandas-stubs~=2.2
Requires-Dist: xdg-base-dirs~=6.0
Provides-Extra: google
Requires-Dist: google-api-python-client==2.166.0; extra == "google"
Requires-Dist: google-auth==2.38.0; extra == "google"
Requires-Dist: google-cloud-bigquery[pandas]==3.29.0; extra == "google"
Requires-Dist: google-cloud-bigquery-storage~=2.30; extra == "google"
Requires-Dist: google-cloud-secret-manager==2.23.2; extra == "google"
Requires-Dist: google-crc32c==1.7.1; extra == "google"
Provides-Extra: amazon
Requires-Dist: boto3==1.37.25; extra == "amazon"
Requires-Dist: boto3-stubs==1.37.25; extra == "amazon"
Provides-Extra: facebook
Requires-Dist: facebook-business==22.0.3; extra == "facebook"
Dynamic: license-file
